[
    {
      "title": "平均收益",
      "keyword": ["平均收益","平均收益是什麼","平均收益意思","平均收益解釋"],
      "answer": ["總收益除以銷售量(AR=TR/Q)，在大多數市場結構中，平均收益等於產品的價格"]
    },
    {
      "title": "邊際收益",
      "keyword": ["邊際收益","邊際收益是什麼","邊際收益意思","邊際收益解釋"],
      "answer": ["銷售量增加一單位所造成的總收益變動金額","舉例: \n 企業銷售量從 100 單位增加到 101 單位，總收益從 $5000 增加到 $5050，那麼該企業的邊際收益為： \n 邊際收益(MR)=(5050-5000)/(101-100)=50/1=50 \n 意味著增加一單位產品的銷售，使得總收益增加 $50"]
    },
    {
      "title": "套牢成本",
      "keyword": ["套牢成本","套牢成本是什麼","套牢成本意思","套牢成本解釋"],
      "answer": ["已經發生且無法回收的成本，指投資者在市場價格下跌後所持有的資產的原始購買成本"]
    },
    {
      "title": "完全競爭廠商",
      "keyword": ["完全競爭廠商","完全競爭廠商是什麼","完全競爭廠商意思","完全競爭廠商解釋"],
      "answer": ["完全競爭市場是一種理想的市場結構，每個賣方所提供的產品完全相同，且沒有任何單一賣方或買方能夠影響市場價格，在完全競爭市場中，廠商的主要目標是利潤最大化(完全競爭廠商:P=MR=MC)","在短期內，廠商可能會有超額利潤或虧損，但在長期內，自由進出市場的機制將使得所有廠商只能獲得正常利潤，利潤為負時，有些廠商會選擇退出市場"]
    },
    {
      "title": "歇業",
      "keyword": ["歇業","歇業是什麼","歇業意思","歇業解釋"],
      "answer": ["企業或商業活動在某一特定期間因市場條件變差而停止生產的決策，主要分為短期歇業和永久歇業，短期期間還需要支付額外費用而永久則是進入清算的程序"]
    },
    {
      "title": "邊際廠商",
      "keyword": ["邊際廠商","邊際廠商是什麼","邊際廠商意思","邊際廠商解釋"],
      "answer": ["指在市場上最接近退出的那個廠商，通常是指那些生產成本接近市場價格或剛好能夠維持盈虧平衡的廠商"]
    }
  ]